exorcist/__about__.py
exorcist/__init__.py
exorcist-0.0.1.dist-info/METADATA
exorcist-0.0.1.dist-info/WHEEL
exorcist-0.0.1.dist-info/licenses/LICENSE.txt
exorcist-0.0.1.dist-info/RECORD
